walrus.py
george_walrus-0.1.5.dist-info/LICENSE
george_walrus-0.1.5.dist-info/METADATA
george_walrus-0.1.5.dist-info/WHEEL
george_walrus-0.1.5.dist-info/entry_points.txt
george_walrus-0.1.5.dist-info/top_level.txt
george_walrus-0.1.5.dist-info/RECORD
